Workbook

Sheet Financial Summary
A1: XRANGE FLAGSHIP DEVELOPMENT PROFILE | D1: BASELINE SCENARIO | M1: 45135
A3: Project: | B3: Base Case | D3: AED:USD | E3: 3.67
A4: Location: | B4: Dubai
A5: Project Type: | B5: XRange | L5: Revenue Escalation | N5: 0.03
A6: Currency | B6: UAE Dirhams | L6: Cost Escalation | N6: 0.03
U7: 0.25010801
A8: IRR | B8: =IRR(C98:N98,0.1) -> 0.41824331 | E8: SPENDING EXPECTATIONS PER PERSON | Q8: IRR | U8: 1.5673434e+08
A9: NPV @ 10% | B9: =NPV(0.1,C98:N98) -> 87312336 | D9: Bay Only | E9: =E23/$B$11 -> 41.89145 | F9: =F23/$B$11 -> 104.78847 | G9: =G23/$B$11 -> 126.97897 | H9: =H23/$B$11 -> 130.78834 | I9: =I23/$B$11 -> 134.71199 | J9: =J23/$B$11 -> 138.75335 | K9: =K23/$B$11 -> 142.91595 | L9: =L23/$B$11 -> 147.20343 | ... N9: =N23/$B$11 -> 156.16812 | Q9: NPV @ 10%
D10: F&B Spend | E10: =E29/$B$11 -> 41.89145 | F10: =F29/$B$11 -> 104.78847 | G10: =G29/$B$11 -> 126.97897 | H10: =H29/$B$11 -> 130.78834 | I10: =I29/$B$11 -> 134.71199 | J10: =J29/$B$11 -> 138.75335 | K10: =K29/$B$11 -> 142.91595 | L10: =L29/$B$11 -> 147.20343 | ... N10: =N29/$B$11 -> 156.16812 | U10: 324454.87
A11: Estimated Distinct Users Per Annum | B11: =H135 -> 140157.4 | D11: Other | E11: =(E24+E25+E35)/$B$11 -> 16.944531 | F11: =(F24+F25+F35)/$B$11 -> 42.385534 | G11: =(G24+G25+G35)/$B$11 -> 51.361294 | H11: =(H24+H25+H35)/$B$11 -> 52.902133 | I11: =(I24+I25+I35)/$B$11 -> 54.489197 | J11: =(J24+J25+J35)/$B$11 -> 56.123872 | K11: =(K24+K25+K35)/$B$11 -> 57.807589 | L11: =(L24+L25+L35)/$B$11 -> 59.541816 | ... N11: =(N24+N25+N35)/$B$11 -> 63.167913 | Q11: Estimated Distinct Users Per Annum | U11: 200
A12: Average Hourly Rate Per Standard Bay (2023) | B12: =D123/B118 -> 199.61476 | D12: TOTAL | E12: =SUM(E9:E11) -> 100.72743 | F12: =SUM(F9:F11) -> 251.96247 | G12: =SUM(G9:G11) -> 305.31923 | H12: =SUM(H9:H11) -> 314.47881 | I12: =SUM(I9:I11) -> 323.91318 | J12: =SUM(J9:J11) -> 333.63057 | K12: =SUM(K9:K11) -> 343.63949 | L12: =SUM(L9:L11) -> 353.94867 | ... N12: =SUM(N9:N11) -> 375.50415 | Q12: Average Hourly Rate Per Standard Bay (2023)
C14: Days of Operation | E14: =365/2 -> 182.5 | F14: 365 | G14: =F14 -> 365 | H14: =G14 -> 365 | I14: =H14 -> 365 | J14: =I14 -> 365 | K14: =J14 -> 365 | L14: =K14 -> 365 | M14: =L14 -> 365 | N14: =M14 -> 365
C15: Number of Bays | E15: =B126 -> 25 | F15: =E15 -> 25 | G15: =F15 -> 25 | H15: =G15 -> 25 | I15: =H15 -> 25 | J15: =I15 -> 25 | K15: =J15 -> 25 | L15: =K15 -> 25 | M15: =L15 -> 25 | N15: =M15 -> 25
C16: Average Bay Occupancy | E16: =G16*(1+E18) -> 0.38584693 | F16: =G16*(1+F18) -> 0.46852842 | G16: =G126 -> 0.55120991 | H16: =G16 -> 0.55120991 | I16: =H16 -> 0.55120991 | J16: =I16 -> 0.55120991 | K16: =J16 -> 0.55120991 | L16: =K16 -> 0.55120991 | M16: =L16 -> 0.55120991 | N16: =M16 -> 0.55120991
C17: Average Daily Bay Rate | E17: =D126*(1+N5)^3 -> 3335.2124 | F17: =E17*(1+$N$5) -> 3435.2687 | G17: =F17*(1+$N$5) -> 3538.3268 | H17: =G17*(1+$N$5) -> 3644.4766 | I17: =H17*(1+$N$5) -> 3753.8109 | J17: =I17*(1+$N$5) -> 3866.4252 | K17: =J17*(1+$N$5) -> 3982.418 | L17: =K17*(1+$N$5) -> 4101.8905 | M17: =L17*(1+$N$5) -> 4224.9472 | N17: =M17*(1+$N$5) -> 4351.6957
C18: Stabilization | E18: -0.3 | F18: -0.15 | G18: 0 | H18: 0 | I18: 0 | J18: 0 | K18: 0 | L18: 0 | M18: 0 | N18: 0
C20: 2023 | D20: =C20+1 -> 2024 | E20: =D20+1 -> 2025 | F20: =E20+1 -> 2026 | G20: =F20+1 -> 2027 | H20: =G20+1 -> 2028 | I20: =H20+1 -> 2029 | J20: =I20+1 -> 2030 | K20: =J20+1 -> 2031 | ... N20: =M20+1 -> 2034
C21: Year 1 | D21: Year 2 | E21: Year 3 | F21: Year 4 | G21: Year 5 | H21: Year 6 | I21: Year 7 | J21: Year 8 | K21: Year 9 | L21: Year 10 | M21: Year 11 | N21: Year 12
A22: REVENUES
A23: Bay Revenues | E23: =E14*E15*E16*E17 -> 5871396.7 | F23: =F14*F15*F16*F17 -> 14686879 | G23: =G14*G15*G16*G17 -> 17797042 | H23: =H14*H15*H16*H17 -> 18330953 | I23: =I14*I15*I16*I17 -> 18880882 | J23: =J14*J15*J16*J17 -> 19447308 | K23: =K14*K15*K16*K17 -> 20030728 | L23: =L14*L15*L16*L17 -> 20631650 | ... N23: =N14*N15*N16*N17 -> 21888117
A24: Memberships | B24: 0 | C24: of Bay Rev | E24: =$B$24*E23 -> 0 | F24: =$B$24*F23 -> 0 | G24: =$B$24*G23 -> 0 | H24: =$B$24*H23 -> 0 | I24: =$B$24*I23 -> 0 | J24: =$B$24*J23 -> 0 | K24: =$B$24*K23 -> 0 | L24: =$B$24*L23 -> 0 | ... N24: =$B$24*N23 -> 0
A25: XRange Academy Revenues | B25: 0.07 | C25: of Bay Rev | E25: =$B$25*E23 -> 410997.77 | F25: =$B$25*F23 -> 1028081.6 | G25: =$B$25*G23 -> 1245792.9 | H25: =$B$25*H23 -> 1283166.7 | I25: =$B$25*I23 -> 1321661.7 | J25: =$B$25*J23 -> 1361311.6 | K25: =$B$25*K23 -> 1402150.9 | L25: =$B$25*L23 -> 1444215.5 | ... N25: =$B$25*N23 -> 1532168.2
A26: Sub-Total Golf Revenues | E26: =SUM(E23:E25) -> 6282394.5 | F26: =SUM(F23:F25) -> 15714961 | G26: =SUM(G23:G25) -> 19042835 | H26: =SUM(H23:H25) -> 19614120 | I26: =SUM(I23:I25) -> 20202544 | J26: =SUM(J23:J25) -> 20808620 | K26: =SUM(K23:K25) -> 21432879 | L26: =SUM(L23:L25) -> 22075865 | ... N26: =SUM(N23:N25) -> 23420285
A27: XRange Dining | B27: 1 | C27: of Golf Revenue | E27: =$B$27*E23 -> 5871396.7 | F27: =$B$27*F23 -> 14686879 | G27: =$B$27*G23 -> 17797042 | H27: =$B$27*H23 -> 18330953 | I27: =$B$27*I23 -> 18880882 | J27: =$B$27*J23 -> 19447308 | K27: =$B$27*K23 -> 20030728 | L27: =$B$27*L23 -> 20631650 | ... N27: =$B$27*N23 -> 21888117
A28: Food & Beverage - Leased | B28: 0 | C28: Rental (AED psm) | D28: 1575 | E28: =$B28*$D28*(1+E$18)*(1+$N$5)^3*E14/365 -> 0 | F28: =$B28*$D28*(1+F$18)*(1+$N$5)^4 -> 0 | G28: =$B28*$D28*(1+G$18)*(1+$N$5)^5 -> 0 | H28: =$B28*$D28*(1+H$18)*(1+$N$5)^6 -> 0 | I28: =$B28*$D28*(1+I$18)*(1+$N$5)^7 -> 0 | J28: =$B28*$D28*(1+J$18)*(1+$N$5)^8 -> 0 | K28: =$B28*$D28*(1+K$18)*(1+$N$5)^9 -> 0 | L28: =$B28*$D28*(1+L$18)*(1+$N$5)^10 -> 0 | M28: =$B28*$D28*(1+M$18)*(1+$N$5)^11 -> 0 | N28: =$B28*$D28*(1+N$18)*(1+$N$5)^12 -> 0
A29: Food & Beverage | E29: =SUM(E27:E28) -> 5871396.7 | F29: =SUM(F27:F28) -> 14686879 | G29: =SUM(G27:G28) -> 17797042 | H29: =SUM(H27:H28) -> 18330953 | I29: =SUM(I27:I28) -> 18880882 | J29: =SUM(J27:J28) -> 19447308 | K29: =SUM(K27:K28) -> 20030728 | L29: =SUM(L27:L28) -> 20631650 | ... N29: =SUM(N27:N28) -> 21888117
A30: VR Arcade | B30: 0 | C30: =C28 -> Rental (AED psm) | D30: 0 | E30: =$B30*$D30*(1+E$18)*(1+$N$5)^3*E14/365 -> 0 | F30: =$B30*$D30*(1+F$18)*(1+$N$5)^4 -> 0 | G30: =$B30*$D30*(1+G$18)*(1+$N$5)^5 -> 0 | H30: =$B30*$D30*(1+H$18)*(1+$N$5)^6 -> 0 | I30: =$B30*$D30*(1+I$18)*(1+$N$5)^7 -> 0 | J30: =$B30*$D30*(1+J$18)*(1+$N$5)^8 -> 0 | K30: =$B30*$D30*(1+K$18)*(1+$N$5)^9 -> 0 | L30: =$B30*$D30*(1+L$18)*(1+$N$5)^10 -> 0 | M30: =$B30*$D30*(1+M$18)*(1+$N$5)^11 -> 0 | N30: =$B30*$D30*(1+N$18)*(1+$N$5)^12 -> 0
A31: Merchandising Store | B31: 1350 | C31: =C30 -> Rental (AED psm) | D31: 100 | E31: =$B31*$D31*(1+E$18)*(1+$N$5)^3*E14/365 -> 51631.351 | F31: =$B31*$D31*(1+F$18)*(1+$N$5)^4 -> 129152.14 | G31: =$B31*$D31*(1+G$18)*(1+$N$5)^5 -> 156502 | H31: =$B31*$D31*(1+H$18)*(1+$N$5)^6 -> 161197.06 | I31: =$B31*$D31*(1+I$18)*(1+$N$5)^7 -> 166032.97 | J31: =$B31*$D31*(1+J$18)*(1+$N$5)^8 -> 171013.96 | K31: =$B31*$D31*(1+K$18)*(1+$N$5)^9 -> 176144.38 | L31: =$B31*$D31*(1+L$18)*(1+$N$5)^10 -> 181428.71 | M31: =$B31*$D31*(1+M$18)*(1+$N$5)^11 -> 186871.57 | N31: =$B31*$D31*(1+N$18)*(1+$N$5)^12 -> 192477.72
A32: Health Club / Salon | B32: 0 | C32: =C31 -> Rental (AED psm) | D32: 0 | E32: =$B32*$D32*(1+E$18)*(1+$N$5)^3*E14/365 -> 0 | F32: =$B32*$D32*(1+F$18)*(1+$N$5)^4 -> 0 | G32: =$B32*$D32*(1+G$18)*(1+$N$5)^5 -> 0 | H32: =$B32*$D32*(1+H$18)*(1+$N$5)^6 -> 0 | I32: =$B32*$D32*(1+I$18)*(1+$N$5)^7 -> 0 | J32: =$B32*$D32*(1+J$18)*(1+$N$5)^8 -> 0 | K32: =$B32*$D32*(1+K$18)*(1+$N$5)^9 -> 0 | L32: =$B32*$D32*(1+L$18)*(1+$N$5)^10 -> 0 | M32: =$B32*$D32*(1+M$18)*(1+$N$5)^11 -> 0 | N32: =$B32*$D32*(1+N$18)*(1+$N$5)^12 -> 0
A33: Sponsorships & Advertising | B33: 5000000 | C33: Estimate | E33: =$B$33*(1+E$18)*(1+$N$6)^3*E14/365 -> 1912272.2 | F33: =$B$33*(1+F$18)*(1+$N$6)^4 -> 4783412.4 | G33: =$B$33*(1+G$18)*(1+$N$6)^5 -> 5796370.4 | H33: =$B$33*(1+H$18)*(1+$N$6)^6 -> 5970261.5 | I33: =$B$33*(1+I$18)*(1+$N$6)^7 -> 6149369.3 | J33: =$B$33*(1+J$18)*(1+$N$6)^8 -> 6333850.4 | K33: =$B$33*(1+K$18)*(1+$N$6)^9 -> 6523865.9 | L33: =$B$33*(1+L$18)*(1+$N$6)^10 -> 6719581.9 | M33: =$B$33*(1+M$18)*(1+$N$6)^11 -> 6921169.4 | N33: =$B$33*(1+N$18)*(1+$N$6)^12 -> 7128804.4
A34: Misc. Revenues | B34: 0 | C34: of Bay Rev | E34: =$B$34*E23 -> 0 | F34: =$B$34*F23 -> 0 | G34: =$B$34*G23 -> 0 | H34: =$B$34*H23 -> 0 | I34: =$B$34*I23 -> 0 | J34: =$B$34*J23 -> 0 | K34: =$B$34*K23 -> 0 | L34: =$B$34*L23 -> 0 | ... N34: =$B$34*N23 -> 0
A35: Sub-Total Other Revenues | E35: =SUM(E30:E34) -> 1963903.6 | F35: =SUM(F30:F34) -> 4912564.6 | G35: =SUM(G30:G34) -> 5952872.4 | H35: =SUM(H30:H34) -> 6131458.5 | I35: =SUM(I30:I34) -> 6315402.3 | J35: =SUM(J30:J34) -> 6504864.4 | K35: =SUM(K30:K34) -> 6700010.3 | L35: =SUM(L30:L34) -> 6901010.6 | ... N35: =SUM(N30:N34) -> 7321282.2
A36: TOTAL OPERATIONAL REVENUES | E36: =E26+E29+E35 -> 14117695 | F36: =F26+F29+F35 -> 35314405 | G36: =G26+G29+G35 -> 42792750 | H36: =H26+H29+H35 -> 44076532 | I36: =I26+I29+I35 -> 45398828 | J36: =J26+J29+J35 -> 46760793 | K36: =K26+K29+K35 -> 48163617 | L36: =L26+L29+L35 -> 49608525 | ... N36: =N26+N29+N35 -> 52629684 | Q36: TOTAL OPERATIONAL REVENUES | U36: 37059186 | V36: 92700908 | W36: 1.1233169e+08 | X36: 1.1570164e+08 | Y36: 1.1917269e+08 | Z36: 1.2274787e+08 | AA36: 1.264303e+08 | AB36: 1.3022321e+08 | AC36: 1.3412991e+08 | AD36: 1.3815381e+08
A38: DIRECT COSTS
A39: Golf Operations | B39: 0.15 | C39: of Bay / Member Revenue | E39: =$B$39*(E23+E24) -> 880709.5 | F39: =$B$39*(F23+F24) -> 2203031.9 | G39: =$B$39*(G23+G24) -> 2669556.3 | H39: =$B$39*(H23+H24) -> 2749643 | I39: =$B$39*(I23+I24) -> 2832132.3 | J39: =$B$39*(J23+J24) -> 2917096.3 | K39: =$B$39*(K23+K24) -> 3004609.2 | L39: =$B$39*(L23+L24) -> 3094747.4 | ... N39: =$B$39*(N23+N24) -> 3283217.5
A40: XRange Technology Servicing Fee | B40: 255000 | C40: USD Annual Fee Adj. for Inflation | E40: =$B$40*$E$3*(1+$N$6)^3 -> 1022628.6 | F40: =$B$40*$E$3*(1+$N$6)^4 -> 1053307.4 | G40: =$B$40*$E$3*(1+$N$6)^5 -> 1084906.6 | H40: =$B$40*$E$3*(1+$N$6)^6 -> 1117453.8 | I40: =$B$40*$E$3*(1+$N$6)^7 -> 1150977.5 | J40: =$B$40*$E$3*(1+$N$6)^8 -> 1185506.8 | K40: =$B$40*$E$3*(1+$N$6)^9 -> 1221072 | L40: =$B$40*$E$3*(1+$N$6)^10 -> 1257704.1 | M40: =$B$40*$E$3*(1+$N$6)^11 -> 1295435.3 | N40: =$B$40*$E$3*(1+$N$6)^12 -> 1334298.3
A41: XRange Academy | B41: 0.5 | C41: of Academy Revenue | E41: =$B$41*E25 -> 205498.88 | F41: =$B$41*F25 -> 514040.78 | G41: =$B$41*G25 -> 622896.47 | H41: =$B$41*H25 -> 641583.37 | I41: =$B$41*I25 -> 660830.87 | J41: =$B$41*J25 -> 680655.8 | K41: =$B$41*K25 -> 701075.47 | L41: =$B$41*L25 -> 722107.73 | ... N41: =$B$41*N25 -> 766084.09
A42: F&B Operations | B42: 0.65 | C42: of F&B Rev | E42: =$B$42*E29 -> 3816407.8 | F42: =$B$42*F29 -> 9546471.6 | G42: =$B$42*G29 -> 11568077 | H42: =$B$42*H29 -> 11915120 | I42: =$B$42*I29 -> 12272573 | J42: =$B$42*J29 -> 12640750 | K42: =$B$42*K29 -> 13019973 | L42: =$B$42*L29 -> 13410572 | ... N42: =$B$42*N29 -> 14227276
A43: VR Arcade | B43: 0.1 | C43: of VR Arcade | E43: =$B$43*E30 -> 0 | F43: =$B$43*F30 -> 0 | G43: =$B$43*G30 -> 0 | H43: =$B$43*H30 -> 0 | I43: =$B$43*I30 -> 0 | J43: =$B$43*J30 -> 0 | K43: =$B$43*K30 -> 0 | L43: =$B$43*L30 -> 0 | ... N43: =$B$43*N30 -> 0
A44: Merchandising Store | B44: 0.1 | C44: of Merchandising | E44: =$B$44*E31 -> 5163.1351 | F44: =$B$44*F31 -> 12915.214 | G44: =$B$44*G31 -> 15650.2 | H44: =$B$44*H31 -> 16119.706 | I44: =$B$44*I31 -> 16603.297 | J44: =$B$44*J31 -> 17101.396 | K44: =$B$44*K31 -> 17614.438 | L44: =$B$44*L31 -> 18142.871 | ... N44: =$B$44*N31 -> 19247.772
A45: Health Club / Salon | B45: 0.1 | C45: of Health Club / Salon | E45: =$B$45*E32 -> 0 | F45: =$B$45*F32 -> 0 | G45: =$B$45*G32 -> 0 | H45: =$B$45*H32 -> 0 | I45: =$B$45*I32 -> 0 | J45: =$B$45*J32 -> 0 | K45: =$B$45*K32 -> 0 | L45: =$B$45*L32 -> 0 | ... N45: =$B$45*N32 -> 0
A46: Sponsorshipos & Advertising | B46: 0.1 | C46: of Sponsorships | E46: =$B$46*E33 -> 191227.23 | F46: =$B$46*F33 -> 478341.24 | G46: =$B$46*G33 -> 579637.04 | H46: =$B$46*H33 -> 597026.15 | I46: =$B$46*I33 -> 614936.93 | J46: =$B$46*J33 -> 633385.04 | K46: =$B$46*K33 -> 652386.59 | L46: =$B$46*L33 -> 671958.19 | ... N46: =$B$46*N33 -> 712880.44
A47: Misc. Revenues | B47: 0.2 | C47: of Misc. Revenue | E47: =$B$47*E34 -> 0 | F47: =$B$47*F34 -> 0 | G47: =$B$47*G34 -> 0 | H47: =$B$47*H34 -> 0 | I47: =$B$47*I34 -> 0 | J47: =$B$47*J34 -> 0 | K47: =$B$47*K34 -> 0 | L47: =$B$47*L34 -> 0 | ... N47: =$B$47*N34 -> 0
A48: DIRECT OPERATIONAL COSTS | E48: =SUM(E39:E47) -> 6121635.2 | F48: =SUM(F39:F47) -> 13808108 | G48: =SUM(G39:G47) -> 16540724 | H48: =SUM(H39:H47) -> 17036946 | I48: =SUM(I39:I47) -> 17548054 | J48: =SUM(J39:J47) -> 18074496 | K48: =SUM(K39:K47) -> 18616731 | L48: =SUM(L39:L47) -> 19175233 | ... N48: =SUM(N39:N47) -> 20343004 | Q48: DIRECT OPERATIONAL COSTS | U48: 16165682 | V48: 38932574 | W48: 46985664 | X48: 48395234 | Y48: 49847091 | Z48: 51342504 | AA48: 52882779 | AB48: 54469263 | AC48: 56103341 | AD48: 57786441
A50: OPERATING PROFIT
A51: Golf Operations | E51: =E26-SUM(E39:E41) -> 4173557.5 | F51: =F26-SUM(F39:F41) -> 11944581 | G51: =G26-SUM(G39:G41) -> 14665476 | H51: =H26-SUM(H39:H41) -> 15105440 | I51: =I26-SUM(I39:I41) -> 15558603 | J51: =J26-SUM(J39:J41) -> 16025361 | K51: =K26-SUM(K39:K41) -> 16506122 | L51: =L26-SUM(L39:L41) -> 17001306 | ... N51: =N26-SUM(N39:N41) -> 18036685 | Q51: Golf Operations | U51: 12644458 | V51: 33133933 | W51: 40341985 | X51: 41552244 | Y51: 42798812 | Z51: 44082776 | AA51: 45405259 | AB51: 46767417 | AC51: 48170440 | AD51: 49615553
A52: F&B Operations | E52: =E29-E42 -> 2054988.8 | F52: =F29-F42 -> 5140407.8 | G52: =G29-G42 -> 6228964.7 | H52: =H29-H42 -> 6415833.7 | I52: =I29-I42 -> 6608308.7 | J52: =J29-J42 -> 6806558 | K52: =K29-K42 -> 7010754.7 | L52: =L29-L42 -> 7221077.3 | ... N52: =N29-N42 -> 7660840.9 | Q52: F&B Operations | U52: 5621010.9 | V52: 14060557 | W52: 17038087 | X52: 17549230 | Y52: 18075706 | Z52: 18617978 | AA52: 19176517 | AB52: 19751813 | AC52: 20344367 | AD52: 20954698
A53: Other Operations | E53: =E35-SUM(E43:E47) -> 1767513.2 | F53: =F35-SUM(F43:F47) -> 4421308.1 | G53: =G35-SUM(G43:G47) -> 5357585.1 | H53: =H35-SUM(H43:H47) -> 5518312.7 | I53: =I35-SUM(I43:I47) -> 5683862.1 | J53: =J35-SUM(J43:J47) -> 5854377.9 | K53: =K35-SUM(K43:K47) -> 6030009.3 | L53: =L35-SUM(L43:L47) -> 6210909.5 | ... N53: =N35-SUM(N43:N47) -> 6589153.9 | Q53: Other Operations | U53: 2628035.8 | V53: 6573843.7 | W53: 7965951.8 | X53: 8204930.4 | Y53: 8451078.3 | Z53: 8704610.6 | AA53: 8965748.9 | AB53: 9234721.4 | AC53: 9511763 | AD53: 9797115.9
A54: OPERATING PROFITS | E54: =SUM(E51:E53) -> 7996059.6 | F54: =SUM(F51:F53) -> 21506297 | G54: =SUM(G51:G53) -> 26252026 | H54: =SUM(H51:H53) -> 27039586 | I54: =SUM(I51:I53) -> 27850774 | J54: =SUM(J51:J53) -> 28686297 | K54: =SUM(K51:K53) -> 29546886 | L54: =SUM(L51:L53) -> 30433293 | ... N54: =SUM(N51:N53) -> 32286680 | Q54: OPERATING PROFITS | U54: 20893505 | V54: 53768334 | W54: 65346024 | X54: 67306404 | Y54: 69325596 | Z54: 71405364 | AA54: 73547525 | AB54: 75753951 | AC54: 78026570 | AD54: 80367367
A56: UNDISTRIBUTED COSTS
A57: LICENSiNG FEE
A58: Initial Fee | B58: 500000 | C58: Initial Brand Rights | D58: LIMITS | E58: =$B$58*$E$3 -> 1835000
A59: Fixed Fee to $5 million | B59: 500000 | C59: Fixed Fee | D59: 5000000 | E59: =$B$59*$E$3*(1+$N$6)^3 -> 2005154 | F59: =$B$59*$E$3*(1+$N$6)^4 -> 2065308.7 | G59: =$B$59*$E$3*(1+$N$6)^5 -> 2127267.9 | H59: =$B$59*$E$3*(1+$N$6)^6 -> 2191086 | I59: =$B$59*$E$3*(1+$N$6)^7 -> 2256818.5 | J59: =$B$59*$E$3*(1+$N$6)^8 -> 2324523.1 | K59: =$B$59*$E$3*(1+$N$6)^9 -> 2394258.8 | L59: =$B$59*$E$3*(1+$N$6)^10 -> 2466086.6 | M59: =$B$59*$E$3*(1+$N$6)^11 -> 2540069.2 | N59: =$B$59*$E$3*(1+$N$6)^12 -> 2616271.2
A60: Performance Fee to $10 million | B60: 0.07 | C60: Fee on Total Rev | D60: 10000000 | E60: =IF(E36>$D$59*(1+$N$6)^3*$E$3,MIN((E36-$D$59*(1+$N$6)^3*$E$3)*$B$60,($D$60-$D$59)*(1+$N$6)^3*$E$3*$B$60),0) -> 0 | F60: =IF(F36>$D$59*(1+$N$6)^4*$E$3,MIN((F36-$D$59*(1+$N$6)^4*$E$3)*$B$60,($D$60-$D$59)*(1+$N$6)^4*$E$3*$B$60),0) -> 1026292.3 | G60: =IF(G36>$D$59*(1+$N$6)^5*$E$3,MIN((G36-$D$59*(1+$N$6)^5*$E$3)*$B$60,($D$60-$D$59)*(1+$N$6)^5*$E$3*$B$60),0) -> 1489087.5 | H60: =IF(H36>$D$59*(1+$N$6)^6*$E$3,MIN((H36-$D$59*(1+$N$6)^6*$E$3)*$B$60,($D$60-$D$59)*(1+$N$6)^6*$E$3*$B$60),0) -> 1533760.2 | I60: =IF(I36>$D$59*(1+$N$6)^7*$E$3,MIN((I36-$D$59*(1+$N$6)^7*$E$3)*$B$60,($D$60-$D$59)*(1+$N$6)^7*$E$3*$B$60),0) -> 1579773 | J60: =IF(J36>$D$59*(1+$N$6)^8*$E$3,MIN((J36-$D$59*(1+$N$6)^8*$E$3)*$B$60,($D$60-$D$59)*(1+$N$6)^8*$E$3*$B$60),0) -> 1627166.2 | K60: =IF(K36>$D$59*(1+$N$6)^9*$E$3,MIN((K36-$D$59*(1+$N$6)^9*$E$3)*$B$60,($D$60-$D$59)*(1+$N$6)^9*$E$3*$B$60),0) -> 1675981.2 | L60: =IF(L36>$D$59*(1+$N$6)^10*$E$3,MIN((L36-$D$59*(1+$N$6)^10*$E$3)*$B$60,($D$60-$D$59)*(1+$N$6)^10*$E$3*$B$60),0) -> 1726260.6 | M60: =IF(M36>$D$59*(1+$N$6)^11*$E$3,MIN((M36-$D$59*(1+$N$6)^11*$E$3)*$B$60,($D$60-$D$59)*(1+$N$6)^11*$E$3*$B$60),0) -> 1778048.4 | N60: =IF(N36>$D$59*(1+$N$6)^12*$E$3,MIN((N36-$D$59*(1+$N$6)^12*$E$3)*$B$60,($D$60-$D$59)*(1+$N$6)^12*$E$3*$B$60),0) -> 1831389.9
A61: Performance Fee to $15 million | B61: 0.07 | C61: Fee on Total Rev | D61: 15000000 | E61: =IF(E36>$D$60*(1+$N$6)^3*$E$3,MIN((E36-$D$60*(1+$N$6)^3*$E$3)*$B$61,($D$61-$D$60)*(1+$N$6)^3*$E$3*$B$61),0) -> 0 | F61: =IF(F36>$D$60*(1+$N$6)^4*$E$3,MIN((F36-$D$60*(1+$N$6)^4*$E$3)*$B$61,($D$61-$D$60)*(1+$N$6)^4*$E$3*$B$61),0) -> 0 | G61: =IF(G36>$D$60*(1+$N$6)^5*$E$3,MIN((G36-$D$60*(1+$N$6)^5*$E$3)*$B$61,($D$61-$D$60)*(1+$N$6)^5*$E$3*$B$61),0) -> 17317.373 | H61: =IF(H36>$D$60*(1+$N$6)^6*$E$3,MIN((H36-$D$60*(1+$N$6)^6*$E$3)*$B$61,($D$61-$D$60)*(1+$N$6)^6*$E$3*$B$61),0) -> 17836.894 | I61: =IF(I36>$D$60*(1+$N$6)^7*$E$3,MIN((I36-$D$60*(1+$N$6)^7*$E$3)*$B$61,($D$61-$D$60)*(1+$N$6)^7*$E$3*$B$61),0) -> 18372.001 | J61: =IF(J36>$D$60*(1+$N$6)^8*$E$3,MIN((J36-$D$60*(1+$N$6)^8*$E$3)*$B$61,($D$61-$D$60)*(1+$N$6)^8*$E$3*$B$61),0) -> 18923.161 | K61: =IF(K36>$D$60*(1+$N$6)^9*$E$3,MIN((K36-$D$60*(1+$N$6)^9*$E$3)*$B$61,($D$61-$D$60)*(1+$N$6)^9*$E$3*$B$61),0) -> 19490.856 | L61: =IF(L36>$D$60*(1+$N$6)^10*$E$3,MIN((L36-$D$60*(1+$N$6)^10*$E$3)*$B$61,($D$61-$D$60)*(1+$N$6)^10*$E$3*$B$61),0) -> 20075.581 | M61: =IF(M36>$D$60*(1+$N$6)^11*$E$3,MIN((M36-$D$60*(1+$N$6)^11*$E$3)*$B$61,($D$61-$D$60)*(1+$N$6)^11*$E$3*$B$61),0) -> 20677.849 | N61: =IF(N36>$D$60*(1+$N$6)^12*$E$3,MIN((N36-$D$60*(1+$N$6)^12*$E$3)*$B$61,($D$61-$D$60)*(1+$N$6)^12*$E$3*$B$61),0) -> 21298.184
A62: Performance Fee for Revenues to $20 million | B62: 0.07 | C62: Fee on Total Rev | D62: 20000000 | E62: =IF(E36>$D$61*(1+$N$6)^3*$E$3,MIN((E36-$D$61*(1+$N$6)^3*$E$3)*$B$62,($D$62-$D$61)*(1+$N$6)^3*$E$3*$B$62),0) -> 0 | F62: =IF(F36>$D$61*(1+$N$6)^4*$E$3,MIN((F36-$D$61*(1+$N$6)^4*$E$3)*$B$62,($D$62-$D$61)*(1+$N$6)^4*$E$3*$B$62),0) -> 0 | G62: =IF(G36>$D$61*(1+$N$6)^5*$E$3,MIN((G36-$D$61*(1+$N$6)^5*$E$3)*$B$62,($D$62-$D$61)*(1+$N$6)^5*$E$3*$B$62),0) -> 0 | H62: =IF(H36>$D$61*(1+$N$6)^6*$E$3,MIN((H36-$D$61*(1+$N$6)^6*$E$3)*$B$62,($D$62-$D$61)*(1+$N$6)^6*$E$3*$B$62),0) -> 0 | I62: =IF(I36>$D$61*(1+$N$6)^7*$E$3,MIN((I36-$D$61*(1+$N$6)^7*$E$3)*$B$62,($D$62-$D$61)*(1+$N$6)^7*$E$3*$B$62),0) -> 0 | J62: =IF(J36>$D$61*(1+$N$6)^8*$E$3,MIN((J36-$D$61*(1+$N$6)^8*$E$3)*$B$62,($D$62-$D$61)*(1+$N$6)^8*$E$3*$B$62),0) -> 0 | K62: =IF(K36>$D$61*(1+$N$6)^9*$E$3,MIN((K36-$D$61*(1+$N$6)^9*$E$3)*$B$62,($D$62-$D$61)*(1+$N$6)^9*$E$3*$B$62),0) -> 0 | L62: =IF(L36>$D$61*(1+$N$6)^10*$E$3,MIN((L36-$D$61*(1+$N$6)^10*$E$3)*$B$62,($D$62-$D$61)*(1+$N$6)^10*$E$3*$B$62),0) -> 0 | M62: =IF(M36>$D$61*(1+$N$6)^11*$E$3,MIN((M36-$D$61*(1+$N$6)^11*$E$3)*$B$62,($D$62-$D$61)*(1+$N$6)^11*$E$3*$B$62),0) -> 0 | N62: =IF(N36>$D$61*(1+$N$6)^12*$E$3,MIN((N36-$D$61*(1+$N$6)^12*$E$3)*$B$62,($D$62-$D$61)*(1+$N$6)^12*$E$3*$B$62),0) -> 0
A63: Performance Fee for Revenues > $20 million | B63: 0.07 | C63: Fee on Total Rev | E63: =IF(E36>$D$62*(1+$N$6)^1*$E$3,(E36-$D$62*(1+$N$6)^3*$E$3)*$B$63,0) -> 0 | F63: =IF(F36>$D$62*(1+$N$6)^4*$E$3,(F36-$D$62*(1+$N$6)^4*$E$3)*$B$63,0) -> 0 | G63: =IF(G36>$D$62*(1+$N$6)^5*$E$3,(G36-$D$62*(1+$N$6)^5*$E$3)*$B$63,0) -> 0 | H63: =IF(H36>$D$62*(1+$N$6)^6*$E$3,(H36-$D$62*(1+$N$6)^6*$E$3)*$B$63,0) -> 0 | I63: =IF(I36>$D$62*(1+$N$6)^7*$E$3,(I36-$D$62*(1+$N$6)^7*$E$3)*$B$63,0) -> 0 | J63: =IF(J36>$D$62*(1+$N$6)^8*$E$3,(J36-$D$62*(1+$N$6)^8*$E$3)*$B$63,0) -> 0 | K63: =IF(K36>$D$62*(1+$N$6)^9*$E$3,(K36-$D$62*(1+$N$6)^9*$E$3)*$B$63,0) -> 0 | L63: =IF(L36>$D$62*(1+$N$6)^10*$E$3,(L36-$D$62*(1+$N$6)^10*$E$3)*$B$63,0) -> 0 | M63: =IF(M36>$D$62*(1+$N$6)^11*$E$3,(M36-$D$62*(1+$N$6)^11*$E$3)*$B$63,0) -> 0 | N63: =IF(N36>$D$62*(1+$N$6)^12*$E$3,(N36-$D$62*(1+$N$6)^12*$E$3)*$B$63,0) -> 0
A64: XRANGE LICENSING FEE | C64: Fees Adj. For Inflation | E64: =SUM(E58:E63) -> 3840154 | F64: =SUM(F58:F63) -> 3091600.9 | G64: =SUM(G58:G63) -> 3633672.8 | H64: =SUM(H58:H63) -> 3742683 | I64: =SUM(I58:I63) -> 3854963.5 | J64: =SUM(J58:J63) -> 3970612.4 | K64: =SUM(K58:K63) -> 4089730.8 | L64: =SUM(L58:L63) -> 4212422.7 | ... N64: =SUM(N58:N63) -> 4468959.3 | Q64: XRANGE LICENSING FEE | S64: Fees Adj. For Inflation | U64: 4323536.3 | V64: 6589949.1 | W64: 8135627.9 | X64: 8379696.7 | Y64: 8631087.6 | Z64: 8890020.2 | AA64: 9156720.8 | AB64: 9431422.5 | AC64: 9714365.1 | AD64: 10005796
A66: SALES & MARKETING
A67: Facility Marketing | B67: 0.05 | C67: on All Revenues | E67: =$B$67*E36 -> 705884.74 | F67: =$B$67*F36 -> 1765720.2 | G67: =$B$67*G36 -> 2139637.5 | H67: =$B$67*H36 -> 2203826.6 | I67: =$B$67*I36 -> 2269941.4 | J67: =$B$67*J36 -> 2338039.6 | K67: =$B$67*K36 -> 2408180.8 | L67: =$B$67*L36 -> 2480426.3 | ... N67: =$B$67*N36 -> 2631484.2
A68: XRange Marketing Fee | B68: 0.03 | C68: on All Revenues | E68: =$B$68*E36 -> 423530.84 | F68: =$B$68*F36 -> 1059432.1 | G68: =$B$68*G36 -> 1283782.5 | H68: =$B$68*H36 -> 1322296 | I68: =$B$68*I36 -> 1361964.8 | J68: =$B$68*J36 -> 1402823.8 | K68: =$B$68*K36 -> 1444908.5 | L68: =$B$68*L36 -> 1488255.8 | ... N68: =$B$68*N36 -> 1578890.5
A69: SALES & MARKETING EXPENSES | E69: =SUM(E67:E68) -> 1129415.6 | F69: =SUM(F67:F68) -> 2825152.4 | G69: =SUM(G67:G68) -> 3423420 | H69: =SUM(H67:H68) -> 3526122.6 | I69: =SUM(I67:I68) -> 3631906.2 | J69: =SUM(J67:J68) -> 3740863.4 | K69: =SUM(K67:K68) -> 3853089.3 | L69: =SUM(L67:L68) -> 3968682 | ... N69: =SUM(N67:N68) -> 4210374.7 | Q69: SALES & MARKETING EXPENSES | U69: 1852959.3 | V69: 4635045.4 | W69: 5616584.4 | X69: 5785081.9 | Y69: 5958634.4 | Z69: 6137393.4 | AA69: 6321515.2 | AB69: 6511160.7 | AC69: 6706495.5 | AD69: 6907690.4
A71: PROPERTY OPERATIONS
A72: Admin & General | B72: 0.02 | C72: on All Revenues | E72: =$B$72*E36 -> 282353.89 | F72: =$B$72*F36 -> 706288.1 | G72: =$B$72*G36 -> 855854.99 | H72: =$B$72*H36 -> 881530.64 | I72: =$B$72*I36 -> 907976.56 | J72: =$B$72*J36 -> 935215.86 | K72: =$B$72*K36 -> 963272.33 | L72: =$B$72*L36 -> 992170.5 | ... N72: =$B$72*N36 -> 1052593.7
A73: Property Operations (FM Staff/Utilities) | B73: 0.05 | C73: on All Revenues | E73: =$B$73*E36 -> 705884.74 | F73: =$B$73*F36 -> 1765720.2 | G73: =$B$73*G36 -> 2139637.5 | H73: =$B$73*H36 -> 2203826.6 | I73: =$B$73*I36 -> 2269941.4 | J73: =$B$73*J36 -> 2338039.6 | K73: =$B$73*K36 -> 2408180.8 | L73: =$B$73*L36 -> 2480426.3 | ... N73: =$B$73*N36 -> 2631484.2
A74: Building Insurance | B74: 0.005 | C74: on All Revenues | E74: =$B$74*E36 -> 70588.474 | F74: =$B$74*F36 -> 176572.02 | G74: =$B$74*G36 -> 213963.75 | H74: =$B$74*H36 -> 220382.66 | I74: =$B$74*I36 -> 226994.14 | J74: =$B$74*J36 -> 233803.96 | K74: =$B$74*K36 -> 240818.08 | L74: =$B$74*L36 -> 248042.63 | ... N74: =$B$74*N36 -> 263148.42
A75: PROPERTY EXPENSES | E75: =SUM(E72:E74) -> 1058827.1 | F75: =SUM(F72:F74) -> 2648580.4 | G75: =SUM(G72:G74) -> 3209456.2 | H75: =SUM(H72:H74) -> 3305739.9 | I75: =SUM(I72:I74) -> 3404912.1 | J75: =SUM(J72:J74) -> 3507059.5 | K75: =SUM(K72:K74) -> 3612271.2 | L75: =SUM(L72:L74) -> 3720639.4 | ... N75: =SUM(N72:N74) -> 3947226.3 | Q75: PROPERTY EXPENSES | U75: 2223551.2 | V75: 5562054.5 | W75: 6739901.3 | X75: 6942098.3 | Y75: 7150361.3 | Z75: 7364872.1 | AA75: 7585818.3 | AB75: 7813392.8 | AC75: 8047794.6 | AD75: 8289228.4
A77: CONTINGENCY | B77: 0.05 | C77: on All Revenues | E77: =$B$77*E36 -> 705884.74 | F77: =$B$77*F36 -> 1765720.2 | G77: =$B$77*G36 -> 2139637.5 | H77: =$B$77*H36 -> 2203826.6 | I77: =$B$77*I36 -> 2269941.4 | J77: =$B$77*J36 -> 2338039.6 | K77: =$B$77*K36 -> 2408180.8 | L77: =$B$77*L36 -> 2480426.3 | ... N77: =$B$77*N36 -> 2631484.2
A79: GROSS OPERATING PROFIT | E79: =E54-E64-E69-E75-E77 -> 1261778.1 | F79: =F54-F64-F69-F75-F77 -> 11175243 | G79: =G54-G64-G69-G75-G77 -> 13845839 | H79: =H54-H64-H69-H75-H77 -> 14261214 | I79: =I54-I64-I69-I75-I77 -> 14689051 | J79: =J54-J64-J69-J75-J77 -> 15129722 | K79: =K54-K64-K69-K75-K77 -> 15583614 | L79: =L54-L64-L69-L75-L77 -> 16051122 | ... N79: =N54-N64-N69-N75-N77 -> 17028636 | Q79: GROSS OPERATING PROFIT | U79: 10640498 | V79: 32346240 | W79: 39237326 | X79: 40414445 | Y79: 41626879 | Z79: 42875685 | AA79: 44161956 | AB79: 45486814 | AC79: 46851419 | AD79: 48256961
A81: Management Fee | B81: 0.02 | C81: on All Revenues | E81: =$B$81*E36 -> 282353.89 | F81: =$B$81*F36 -> 706288.1 | G81: =$B$81*G36 -> 855854.99 | H81: =$B$81*H36 -> 881530.64 | I81: =$B$81*I36 -> 907976.56 | J81: =$B$81*J36 -> 935215.86 | K81: =$B$81*K36 -> 963272.33 | L81: =$B$81*L36 -> 992170.5 | ... N81: =$B$81*N36 -> 1052593.7
A83: EBITDA | B83: Cap Rate | E83: =E79-E81 -> 979424.22 | F83: =F79-F81 -> 10468955 | G83: =G79-G81 -> 12989984 | H83: =H79-H81 -> 13379684 | I83: =I79-I81 -> 13781074 | J83: =J79-J81 -> 14194506 | K83: =K79-K81 -> 14620341 | L83: =L79-L81 -> 15058952 | ... N83: =N79-N81 -> 15976042 | Q83: EBITDA | R83: Cap Rate | U83: 7354562.8 | V83: 24126707 | W83: 29277186 | X83: 30155501 | Y83: 31060166 | Z83: 31991971 | AA83: 32951730 | AB83: 33940282 | AC83: 34958491 | AD83: 36007245
A84: TERMINAL VALUE | B84: 0.09 | N84: =N83/B84 -> 1.7751158e+08 | Q84: TERMINAL VALUE | R84: 0.09 | AD84: 4.0008051e+08
A86: CAPITAL EXPENDITURES | B86: TOTAL | C86: YEAR 1 | D86: YEAR 2 | E86: YEAR 3
A87: Land & Infrastructure Costs | B87: =SUM(C87:E87) -> 0 | C87: =$B104*C104*(1+$N$6)^1 -> 0 | D87: =$B104*D104*(1+$N$6)^2 -> 0 | E87: =$B104*E104*(1+$N$6)^3 -> 0
A88: Design & Management Fee Costs | B88: =SUM(C88:E88) -> 1145912.8 | C88: =$B105*C105*(1+$N$6)^1 -> 447543.53 | D88: =$B105*D105*(1+$N$6)^2 -> 460969.83 | E88: =$B105*E105*(1+$N$6)^3 -> 237399.46
A89: Construction Costs | B89: =SUM(C89:E89) -> 8232802.9 | C89: =$B106*C106*(1+$N$6)^1 -> 1331974.8 | D89: =$B106*D106*(1+$N$6)^2 -> 5487736.1 | E89: =$B106*E106*(1+$N$6)^3 -> 1413092
A90: Specialist Golf Equipment Costs | B90: =SUM(C90:E90) -> 14205451 | C90: =$B107*C107*(1+$N$6)^1 -> 0 | D90: =$B107*D107*(1+$N$6)^2 -> 0 | E90: =$B107*E107*(1+$N$6)^3 -> 14205451
A91: Sales & Marketing | B91: =SUM(C91:E91) -> 2387372.6 | C91: =$B108*C108*(1+$N$6)^1 -> 386250 | D91: =$B108*D108*(1+$N$6)^2 -> 1591350 | E91: =$B108*E108*(1+$N$6)^3 -> 409772.62
A92: Pre-Opening Expenses | B92: =SUM(C92:E92) -> 2458635.8 | C92: =$B109*C109*(1+$N$6)^1 -> 0 | D92: =$B109*D109*(1+$N$6)^2 -> 0 | E92: =$B109*E109*(1+$N$6)^3 -> 2458635.8
A93: G&A | B93: =SUM(C93:E93) -> 345671.62 | C93: =$B110*C110*(1+$N$6)^1 -> 135004.25 | D93: =$B110*D110*(1+$N$6)^2 -> 139054.37 | E93: =$B110*E110*(1+$N$6)^3 -> 71613.002
A95: Replacement Reserve - Building | B95: 0.025 | C95: on All Revenues | E95: =$B$95*E36 -> 352942.37 | F95: =$B$95*F36 -> 882860.12 | G95: =$B$95*G36 -> 1069818.7 | H95: =$B$95*H36 -> 1101913.3 | I95: =$B$95*I36 -> 1134970.7 | J95: =$B$95*J36 -> 1169019.8 | K95: =$B$95*K36 -> 1204090.4 | L95: =$B$95*L36 -> 1240213.1 | ... N95: =$B$95*N36 -> 1315742.1
A96: Replacement Reserve - XRange Tech | B96: 0.015 | C96: on Bay Revenue | E96: =$B$96*E23 -> 88070.95 | F96: =$B$96*F23 -> 220303.19 | G96: =$B$96*G23 -> 266955.63 | H96: =$B$96*H23 -> 274964.3 | I96: =$B$96*I23 -> 283213.23 | J96: =$B$96*J23 -> 291709.63 | K96: =$B$96*K23 -> 300460.92 | L96: =$B$96*L23 -> 309474.74 | ... N96: =$B$96*N23 -> 328321.75
A98: OVEALL CASH FLOW | C98: =C83+C84-SUM(C87:C93) -> -2300772.6 | D98: =D83+D84-SUM(D87:D93) -> -7679110.3 | E98: =E83+E84-SUM(E87:E96) -> -18257553 | F98: =F83+F84-SUM(F87:F96) -> 9365791.4 | G98: =G83+G84-SUM(G87:G96) -> 11653210 | H98: =H83+H84-SUM(H87:H96) -> 12002806 | I98: =I83+I84-SUM(I87:I96) -> 12362890 | J98: =J83+J84-SUM(J87:J96) -> 12733777 | K98: =K83+K84-SUM(K87:K96) -> 13115790 | L98: =L83+L84-SUM(L87:L96) -> 13509264 | ... N98: =N83+N84-SUM(N87:N96) -> 1.9184355e+08
A101: CAPEX ASSUMPTIONS | B101: SEE 'HARD + SOFT COSTS' WORKSHEET
A103: CAPEX | B103: TOTAL | C103: YEAR 1 | D103: YEAR 2 | E103: YEAR 3
A104: Land & Infr | B104: 0 | C104: 1 | D104: 0 | E104: 0
A105: Design & XRange Fees | B105: ='Hard + Soft Costs'!E36 -> 1086270.7 | C105: 0.4 | D105: 0.4 | E105: 0.2
A106: Construction Costs + Contingency | B106: ='Hard + Soft Costs'!E24 -> 7759076.4 | C106: 0.16666667 | D106: 0.66666667 | E106: 0.16666667
A107: Specialist Golf Equipment | B107: ='Hard + Soft Costs'!E150 -> 13000000 | C107: 0 | D107: 0 | E107: 1
A108: Sales & Marketing | B108: =2250000*E3/3.67 -> 2250000 | C108: 0.16666667 | D108: 0.66666667 | E108: 0.16666667
A109: Pre-Opening | B109: =2250000*E3/3.67 -> 2250000 | C109: 0 | D109: 0 | E109: 1
A110: G&A | B110: =SUM(B105:B107)*0.015 -> 327680.21 | C110: 0.4 | D110: 0.4 | E110: 0.2
A111: TOTAL | B111: =SUM(B104:B110) -> 26673027
A112: Unescalated
A114: BAY REVENUE SUMMARY | B114: SEE 'BAY REVENUE' WORKSHEET FOR BUILD-UP OF REVENEUS
B115: AED | C115: USD
A116: Base Hourly Rate (Standard Bay) | B116: ='Bay Revenue'!B25 -> 200 | C116: =B116/E3 -> 54.495913
E117: Peak | F117: Non-Peak | H117: Peak | I117: Non-Peak
A118: Hours of Operation | B118: =('Bay Revenue'!G28+'Bay Revenue'!I28)*'Bay Revenue'!C28/'Bay Revenue'!C30+('Bay Revenue'!G29+'Bay Revenue'!I29)*'Bay Revenue'!C29/'Bay Revenue'!C30 -> 15.290411 | D118: Weekdays | E118: ='Bay Revenue'!I28 -> 7 | F118: ='Bay Revenue'!G28 -> 7 | G118: Weekends | H118: ='Bay Revenue'!I29 -> 9 | I118: ='Bay Revenue'!G29 -> 8
A120: BAY REVENUE | B120: # BAYS | C120: % OF STANDARD | D120: DAILY BAY RATE | E120: REV POTENTIAL | G120: USAGE | H120: REVENUE
...

Sheet Bay Revenue
A1: XRANGE - BREAKDOWN OF BAY REVENUE BY WEEKDAY/WEEKEND AND PEAK/NON-PEAK | H1: ='Financial Summary'!M1 -> 45135
A3: SUMMARY
A5: BAY REVENUE | B5: # BAYS | C5: % OF STANDARD | D5: DAILY BAY RATE | E5: REV POTENTIAL | G5: REV EFFICIENCY | H5: REVENUE
E6: =B24 -> AED | F6: =C24 -> USD | H6: =B24 -> AED | I6: =C24 -> USD
A7: Mini-Bays | B7: 0 | C7: =D7/D8 -> #DIV/0! | D7: =E7/B7/$C30 -> #DIV/0! | E7: =E64+E86+E110+E132 -> 0 | F7: =F64+F86+F110+F132 -> 0 | G7: =H7/E7 -> #DIV/0! | H7: =H64+H86+H110+H132 -> 0 | I7: =I64+I86+I110+I132 -> 0
A8: Standard Bays | B8: 25 | C8: 1 | D8: =E8/B8/$C30 -> 3052.1918 | E8: =E65+E87+E111+E133 -> 27851250 | F8: =F65+F87+F111+F133 -> 7588896.5 | G8: =H8/E8 -> 0.55120991 | H8: =H65+H87+H111+H133 -> 15351885 | I8: =I65+I87+I111+I133 -> 4183074.9
A9: Premium Bays | B9: 0 | C9: =D9/D8 -> #DIV/0! | D9: =E9/B9/$C30 -> #DIV/0! | E9: =E66+E88+E112+E134 -> 0 | F9: =F66+F88+F112+F134 -> 0 | G9: =H9/E9 -> #DIV/0! | H9: =H66+H88+H112+H134 -> 0 | I9: =I66+I88+I112+I134 -> 0
A10: Hospitality Bays | B10: 0 | C10: =D10/D8 -> #DIV/0! | D10: =E10/B10/$C30 -> #DIV/0! | E10: =E67+E89+E113+E135 -> 0 | F10: =F67+F89+F113+F135 -> 0 | G10: =H10/E10 -> #DIV/0! | H10: =H67+H89+H113+H135 -> 0 | I10: =I67+I89+I113+I135 -> 0
A11: TOTAL | B11: =SUM(B7:B10) -> 25 | D11: =E11/B11/$C30 -> 3052.1918 | E11: =SUM(E7:E10) -> 27851250 | F11: =SUM(F7:F10) -> 7588896.5 | G11: =H11/E11 -> 0.55120991 | H11: =SUM(H7:H10) -> 15351885 | I11: =SUM(I7:I10) -> 4183074.9
A12: Unescalated
A14: DISTINCT USERS | B14: # BAYS | C14: HOURS USED PER BAY | F14: NUMBER OF XRANGERS
C15: Daily | D15: Per Annum | E15: All Bays | F15: Users Per Bay | G15: Avg Time (Hrs) | H15: Xrangers | I15: Per Bay
A16: Mini-Bays | B16: =B7 -> 0 | C16: =(($G$28+$I$28)*$C$28/$C$30+($G$29+$I$29)*$C$29/$C$30)*G7 -> #DIV/0! | D16: =E16/B16 -> #DIV/0! | E16: =E73+E95+E119+E141 -> 0 | F16: =H16/E16*G16 -> #DIV/0! | G16: =(G141*H141+G119*H119+G95*H95+G73*H73)/H16 -> #DIV/0! | H16: =H73+H95+H119+H141 -> 0 | I16: =H16/B16 -> #DIV/0!
A17: Standard Bays | B17: =B8 -> 25 | C17: =(($G$28+$I$28)*$C$28/$C$30+($G$29+$I$29)*$C$29/$C$30)*G8 -> 8.428226 | D17: =E17/B17 -> 2803.148 | E17: =E74+E96+E120+E142 -> 70078.699 | F17: =H17/E17*G17 -> 4 | G17: =(G142*H142+G120*H120+G96*H96+G74*H74)/H17 -> 2 | H17: =H74+H96+H120+H142 -> 140157.4 | I17: =H17/B17 -> 5606.2959
A18: Premium Bays | B18: =B9 -> 0 | C18: =(($G$28+$I$28)*$C$28/$C$30+($G$29+$I$29)*$C$29/$C$30)*G9 -> #DIV/0! | D18: =E18/B18 -> #DIV/0! | E18: =E75+E97+E121+E143 -> 0 | F18: =H18/E18*G18 -> #DIV/0! | G18: =(G143*H143+G121*H121+G97*H97+G75*H75)/H18 -> #DIV/0! | H18: =H75+H97+H121+H143 -> 0 | I18: =H18/B18 -> #DIV/0!
A19: Hospitality Bays | B19: =B10 -> 0 | C19: =(($G$28+$I$28)*$C$28/$C$30+($G$29+$I$29)*$C$29/$C$30)*G10 -> #DIV/0! | D19: =E19/B19 -> #DIV/0! | E19: =E76+E98+E122+E144 -> 0 | F19: =H19/E19*G19 -> #DIV/0! | G19: =(G144*H144+G122*H122+G98*H98+G76*H76)/H19 -> #DIV/0! | H19: =H76+H98+H122+H144 -> 0 | I19: =H19/B19 -> #DIV/0!
A20: TOTAL | B20: =SUM(B16:B19) -> 25 | C20: =(($G$28+$I$28)*$C$28/$C$30+($G$29+$I$29)*$C$29/$C$30)*G11 -> 8.428226 | D20: =E20/B20 -> 2803.148 | E20: =SUM(E16:E19) -> 70078.699 | H20: =SUM(H16:H19) -> 140157.4 | I20: =H20/B20 -> 5606.2959
A23: BAY REVENUE USAGE & REVENUE ASSUMPTIONS
B24: AED | C24: USD
A25: Base Hourly Rate (Standard Bay) | B25: 200 | C25: =B25/'Financial Summary'!$E$3 -> 54.495913 | E25: Assumed Hours | F25: Weekdays | G25: 10am to 12am | H25: Weekdays | I25: 9am to 2am
A27: Facility Timing | B27: Distribution | C27: Total | E27: Peak / Non-Peak | F27: Non-Peak Hours | H27: Peak Hours
A28: Weekdays (M-T-W-TH) | B28: 4 | C28: =B28*52 -> 208 | E28: Weekdays | F28: 10 AM to 5PM | G28: 7 | H28: 5 PM to 12 AM | I28: 7
A29: Weekends (F-Sa-Su) | B29: 3 | C29: =B29*52+1 -> 157 | E29: Weekends | F29: 9 AM to 5 PM | G29: 8 | H29: 5 PM to 2 AM | I29: 9
C30: =SUM(C28:C29) -> 365
A32: Summary | B32: Vis/Day | C32: Vis/Bay/Day | D32: Daily Unique Visitors | E32: Bay Revenue | F32: Rev/Visitor
A33: Weekday Non-Peak | B33: =D33/C28 -> 72.814442 | C33: =B33/$B$68 -> 2.9125777 | D33: =H77 -> 15145.404 | E33: =H68 -> 1135905.3 | F33: =E33/D33 -> 75
A34: Weekday Peak | B34: =D34/C28 -> 145.62888 | C34: =B34/$B$68 -> 5.8251554 | D34: =H99 -> 30290.808 | E34: =H90 -> 3029080.8 | F34: =E34/D34 -> 100
A35: Weekday | B35: =D35/C28 -> 218.44333 | C35: =B35/$B$68 -> 8.737733 | D35: =SUM(D33:D34) -> 45436.212 | E35: =SUM(E33:E34) -> 4164986.1 | F35: =E35/D35 -> 91.666667
A36: Weekend Non-Peak | B36: =D36/C29 -> 166.43301 | C36: =B36/$B$68 -> 6.6573204 | D36: =H123 -> 26129.983 | E36: =H114 -> 2612998.3 | F36: =E36/D36 -> 100
A37: Weekend Peak | B37: =D37/C29 -> 436.88665 | C37: =B37/$B$68 -> 17.475466 | D37: =H145 -> 68591.204 | E37: =H136 -> 8573900.5 | F37: =E37/D37 -> 125
A38: Weekend | B38: =D38/C29 -> 603.31966 | C38: =B38/$B$68 -> 24.132786 | D38: =SUM(D36:D37) -> 94721.187 | E38: =SUM(E36:E37) -> 11186899 | F38: =E38/D38 -> 118.10345
A39: TOTALS | B39: =D39/C30 -> 383.99287 | C39: =B39/$B$68 -> 15.359715 | D39: =D35+D38 -> 140157.4 | E39: =E35+E38 -> 15351885 | F39: =E39/D39 -> 109.53318
A40: Non-Escalated
A42: Average Base Rates By Time | B42: =B24 -> AED | C42: =C24 -> USD | D42: Total Hours / Bay | E42: Mini-Bay | F42: Standard Bay | G42: Premium Bay | H42: Hospitality Bay | I42: Overall | K42: SENSITIVITY
A43: Weekday Non-Peak | B43: =B25*(1+B49+B51) -> 150 | C43: =B43/'Financial Summary'!$E$3 -> 40.871935 | D43: =G28*C28 -> 1456 | E43: =5%*(1+K43) -> 0.069347088 | F43: =15%*(1+K43) -> 0.20804126 | G43: =5%*(1+K43) -> 0.069347088 | H43: =5%*(1+K43) -> 0.069347088 | I43: =G68 -> 0.20804126 | K43: 0.38694175
A44: Weekday Peak | B44: =B25*(1+B49+B52) -> 200 | C44: =B44/'Financial Summary'!$E$3 -> 54.495913 | D44: =I28*C28 -> 1456 | E44: =20%*(1+K43) -> 0.27738835 | F44: =30%*(1+K43) -> 0.41608253 | G44: =20%*(1+K43) -> 0.27738835 | H44: =15%*(1+K43) -> 0.20804126 | I44: =G90 -> 0.41608253 | K44: ='Financial Summary'!B11 -> 140157.4
A45: Weekend Non-Peak | B45: =B25*(1+B50+B51) -> 200 | C45: =B45/'Financial Summary'!$E$3 -> 54.495913 | D45: =G29*C29 -> 1256 | E45: =30%*(1+K43) -> 0.41608253 | F45: =30%*(1+K43) -> 0.41608253 | G45: =20%*(1+K43) -> 0.27738835 | H45: =15%*(1+K43) -> 0.20804126 | I45: =G114 -> 0.41608253
A46: Weekend Peak | B46: =B25*(1+B50+B52) -> 250 | C46: =B46/'Financial Summary'!$E$3 -> 68.119891 | D46: =I29*C29 -> 1413 | E46: =50%*(1+K43) -> 0.69347088 | F46: =70%*(1+K43) -> 0.97085923 | G46: =55%*(1+K43) -> 0.76281796 | H46: =35%*(1+K43) -> 0.48542961 | I46: =G136 -> 0.97085923
E47: Bay Usage
A48: Peak / Non-Peak Adjustments | D48: Bay Rev Per Hour | E48: Mini-Bay | F48: Standard Bay | G48: Premium Bay | H48: Hospitality Bay | I48: Avg Hourly Rate
A49: Weekday Discount | B49: -0.1 | D49: Weekday Non-Peak | E49: =D64/$B$60 -> 120 | F49: =D65/$B$60 -> 150 | G49: =D66/$B$60 -> 600 | H49: =D67/$B$60 -> 1800 | I49: =H68/E77 -> 150 | K49: =H20 -> 140157.4
A50: Weekend Premium | B50: 0.15 | D50: Weekday Peak | E50: =D86/$B$82 -> 160 | F50: =D87/$B$82 -> 200 | G50: =D88/$B$82 -> 800 | H50: =D89/$B$82 -> 2400 | I50: =H90/E99 -> 200
A51: Daily Non-Peak Discount | B51: -0.15 | D51: Weekend Non-Peak | E51: =D110/$B$106 -> 160 | F51: =D111/$B$106 -> 200 | G51: =D112/$B$106 -> 800 | H51: =D113/$B$106 -> 2400 | I51: =H114/E123 -> 200
A52: Daily Peak Premium | B52: 0.1 | D52: Weekend Peak | E52: =D132/$B$128 -> 200 | F52: =D133/$B$128 -> 250 | G52: =D134/$B$128 -> 1000 | H52: =D135/$B$128 -> 3000 | I52: =H136/E145 -> 250
D53: Avg Rate - Bay Type | E53: =D7/(($G$28+$I$28)*$C$28/$C$30+($G$29+$I$29)*$C$29/$C$30) -> #DIV/0! | F53: =D8/(($G$28+$I$28)*$C$28/$C$30+($G$29+$I$29)*$C$29/$C$30) -> 199.61476 | G53: =D9/(($G$28+$I$28)*$C$28/$C$30+($G$29+$I$29)*$C$29/$C$30) -> #DIV/0! | H53: =D10/(($G$28+$I$28)*$C$28/$C$30+($G$29+$I$29)*$C$29/$C$30) -> #DIV/0!
A55: A: WEEKDAY SUMMARY | B55: TOTAL DAYS | C55: =C28 -> 208 | D55: TOTAL HOURS | E55: =SUM(D43:D44) -> 2912 | F55: =E55/C55 -> 14 | G55: =G28 -> 7 | H55: =I28 -> 7
A57: A.1: WEEKDAY NON-PEAK | B57: TOTAL DAYS | C57: =C55 -> 208 | D57: NON-PEAK HRS | E57: =D43 -> 1456 | F57: =E57/C57 -> 7 | G57: =H77 -> 15145.404 | H57: XRangers
G58: =G57/C28 -> 72.814442 | H58: XRangers per NON-PEAK weekday
G59: =G58/F57 -> 10.402063 | H59: XRangers per hour (NON-PEAK weekday)
A60: Hours of Operation | B60: =G28 -> 7
A62: BAY REVENUE | B62: # BAYS | C62: % OF STANDARD | D62: DAILY BAY RATE | E62: REV POTENTIAL | G62: USAGE | H62: REVENUE
E63: =B24 -> AED | F63: =C42 -> USD | H63: =B42 -> AED | I63: =C42 -> USD
A64: Mini-Bays | B64: =B16 -> 0 | C64: 0.8 | D64: =C64*D65 -> 840 | E64: =B64*D64*$C$28 -> 0 | F64: =E64/'Financial Summary'!$E$3 -> 0 | G64: =E43 -> 0.069347088 | H64: =E64*G64 -> 0 | I64: =H64/'Financial Summary'!$E$3 -> 0
A65: Standard Bays | B65: =B17 -> 25 | C65: 1 | D65: =B43*C65*B60 -> 1050 | E65: =B65*D65*$C$28 -> 5460000 | F65: =E65/'Financial Summary'!$E$3 -> 1487738.4 | G65: =F43 -> 0.20804126 | H65: =E65*G65 -> 1135905.3 | I65: =H65/'Financial Summary'!$E$3 -> 309510.98
A66: Premium Bays | B66: =B18 -> 0 | C66: 4 | D66: =C66*D65 -> 4200 | E66: =B66*D66*$C$28 -> 0 | F66: =E66/'Financial Summary'!$E$3 -> 0 | G66: =G43 -> 0.069347088 | H66: =E66*G66 -> 0 | I66: =H66/'Financial Summary'!$E$3 -> 0
A67: Hospitality Bays | B67: =B19 -> 0 | C67: 12 | D67: =D65*C67 -> 12600 | E67: =B67*D67*$C$28 -> 0 | F67: =E67/'Financial Summary'!$E$3 -> 0 | G67: =H43 -> 0.069347088 | H67: =E67*G67 -> 0 | I67: =H67/'Financial Summary'!$E$3 -> 0
A68: TOTAL | B68: =SUM(B64:B67) -> 25 | D68: =E68/B68/$C28 -> 1050 | E68: =SUM(E64:E67) -> 5460000 | F68: =SUM(F64:F67) -> 1487738.4 | G68: =H68/E68 -> 0.20804126 | H68: =SUM(H64:H67) -> 1135905.3 | I68: =SUM(I64:I67) -> 309510.98
A69: Unescalated
A71: DISTINCT USERS | B71: # BAYS | C71: HOURS USED PER BAY | F71: NUMBER OF XRANGERS
C72: Daily | D72: Per Annum | E72: All Bays | F72: Users Per Bay | G72: Avg Time (Hrs) | H72: Xrangers | I72: Per Bay
A73: Mini-Bays | B73: =B64 -> 0 | C73: =G64*$B$60 -> 0.48542961 | D73: =C73*$C$28 -> 100.96936 | E73: =D73*B73 -> 0 | F73: 4 | G73: 2 | H73: =E73/G73*F73 -> 0 | I73: =H73/B73 -> #DIV/0!
A74: Standard Bays | B74: =B65 -> 25 | C74: =G65*$B$60 -> 1.4562888 | D74: =C74*$C$28 -> 302.90808 | E74: =D74*B74 -> 7572.702 | F74: 4 | G74: 2 | H74: =E74/G74*F74 -> 15145.404 | I74: =H74/B74 -> 605.81616
A75: Premium Bays | B75: =B66 -> 0 | C75: =G66*$B$60 -> 0.48542961 | D75: =C75*$C$28 -> 100.96936 | E75: =D75*B75 -> 0 | F75: 8 | G75: 2.3 | H75: =E75/G75*F75 -> 0 | I75: =H75/B75 -> #DIV/0!
A76: Hospitality Bays | B76: =B67 -> 0 | C76: =G67*$B$60 -> 0.48542961 | D76: =C76*$C$28 -> 100.96936 | E76: =D76*B76 -> 0 | F76: 12 | G76: 2.5 | H76: =E76/G76*F76 -> 0 | I76: =H76/B76 -> #DIV/0!
A77: TOTAL | B77: =SUM(B73:B76) -> 25 | C77: =D77/C28 -> 1.4562888 | D77: =E77/B77 -> 302.90808 | E77: =SUM(E73:E76) -> 7572.702 | H77: =SUM(H73:H76) -> 15145.404 | I77: =H77/B77 -> 605.81616
A79: A.2: WEEKDAY PEAK | B79: TOTAL DAYS | C79: =C55 -> 208 | D79: PEAK HRS | E79: =D44 -> 1456 | F79: =E79/C79 -> 7 | G79: =H99 -> 30290.808 | H79: XRangers
G80: =G79/C28 -> 145.62888 | H80: XRangers per PEAK weekday
G81: =G80/F79 -> 20.804126 | H81: XRangers per hour (PEAK weekday)
A82: Hours of Operation | B82: =I28 -> 7
A84: BAY REVENUE | B84: # BAYS | C84: % OF STANDARD | D84: DAILY BAY RATE | E84: REV POTENTIAL | G84: USAGE | H84: REVENUE
E85: =E63 -> AED | F85: =F63 -> USD | H85: =H63 -> AED | I85: =I63 -> USD
A86: Mini-Bays | B86: =B73 -> 0 | C86: 0.8 | D86: =C86*D87 -> 1120 | E86: =B86*D86*$C$28 -> 0 | F86: =E86/'Financial Summary'!$E$3 -> 0 | G86: =E44 -> 0.27738835 | H86: =E86*G86 -> 0 | I86: =H86/'Financial Summary'!$E$3 -> 0
A87: Standard Bays | B87: =B74 -> 25 | C87: 1 | D87: =B44*C87*B82 -> 1400 | E87: =B87*D87*$C$28 -> 7280000 | F87: =E87/'Financial Summary'!$E$3 -> 1983651.2 | G87: =F44 -> 0.41608253 | H87: =E87*G87 -> 3029080.8 | I87: =H87/'Financial Summary'!$E$3 -> 825362.61
A88: Premium Bays | B88: =B75 -> 0 | C88: 4 | D88: =C88*D87 -> 5600 | E88: =B88*D88*$C$28 -> 0 | F88: =E88/'Financial Summary'!$E$3 -> 0 | G88: =G44 -> 0.27738835 | H88: =E88*G88 -> 0 | I88: =H88/'Financial Summary'!$E$3 -> 0
A89: Hospitality Bays | B89: =B76 -> 0 | C89: 12 | D89: =D87*C89 -> 16800 | E89: =B89*D89*$C$28 -> 0 | F89: =E89/'Financial Summary'!$E$3 -> 0 | G89: =H44 -> 0.20804126 | H89: =E89*G89 -> 0 | I89: =H89/'Financial Summary'!$E$3 -> 0
A90: TOTAL | B90: =SUM(B86:B89) -> 25 | D90: =E90/B90/$C28 -> 1400 | E90: =SUM(E86:E89) -> 7280000 | F90: =SUM(F86:F89) -> 1983651.2 | G90: =H90/E90 -> 0.41608253 | H90: =SUM(H86:H89) -> 3029080.8 | I90: =SUM(I86:I89) -> 825362.61
A91: Unescalated
A93: DISTINCT USERS | B93: # BAYS | C93: HOURS USED PER BAY | F93: NUMBER OF XRANGERS
C94: Daily | D94: Per Annum | E94: All Bays | F94: Users Per Bay | G94: Avg Time (Hrs) | H94: Xrangers | I94: Per Bay
A95: Mini-Bays | B95: =B86 -> 0 | C95: =G86*$B$82 -> 1.9417185 | D95: =C95*$C$28 -> 403.87744 | E95: =D95*B95 -> 0 | F95: 4 | G95: 2 | H95: =E95/G95*F95 -> 0 | I95: =H95/B95 -> #DIV/0!
A96: Standard Bays | B96: =B87 -> 25 | C96: =G87*$B$82 -> 2.9125777 | D96: =C96*$C$28 -> 605.81616 | E96: =D96*B96 -> 15145.404 | F96: 4 | G96: 2 | H96: =E96/G96*F96 -> 30290.808 | I96: =H96/B96 -> 1211.6323
A97: Premium Bays | B97: =B88 -> 0 | C97: =G88*$B$82 -> 1.9417185 | D97: =C97*$C$28 -> 403.87744 | E97: =D97*B97 -> 0 | F97: 8 | G97: 2.3 | H97: =E97/G97*F97 -> 0 | I97: =H97/B97 -> #DIV/0!
A98: Hospitality Bays | B98: =B89 -> 0 | C98: =G89*$B$82 -> 1.4562888 | D98: =C98*$C$28 -> 302.90808 | E98: =D98*B98 -> 0 | F98: 12 | G98: 2.5 | H98: =E98/G98*F98 -> 0 | I98: =H98/B98 -> #DIV/0!
A99: TOTAL | B99: =SUM(B95:B98) -> 25 | C99: =D99/C28 -> 2.9125777 | D99: =E99/B99 -> 605.81616 | E99: =SUM(E95:E98) -> 15145.404 | H99: =SUM(H95:H98) -> 30290.808 | I99: =H99/B99 -> 1211.6323
A101: B: WEEKEND SUMMARY | B101: TOTAL DAYS | C101: =C29 -> 157 | D101: TOTAL HOURS | E101: =D45+D46 -> 2669 | F101: =E101/C101 -> 17 | G101: =G29 -> 8 | H101: =I29 -> 9
A103: B.1: WEEKEND NON-PEAK | B103: TOTAL DAYS | C103: =C101 -> 157 | D103: NON PEAK HRS | E103: =D45 -> 1256 | F103: =E103/C103 -> 8 | G103: =H123 -> 26129.983 | H103: XRangers
G104: =G103/C29 -> 166.43301 | H104: XRangers per NON-PEAK weekend
G105: =G104/F103 -> 20.804126 | H105: XRangers per hour (NON-PEAK weekend)
A106: Hours of Operation | B106: =G29 -> 8
A108: BAY REVENUE | B108: # BAYS | C108: % OF STANDARD | D108: DAILY BAY RATE | E108: REV POTENTIAL | G108: USAGE | H108: REVENUE
E109: =E85 -> AED | F109: =F85 -> USD | H109: =H85 -> AED | I109: =I85 -> USD
A110: Mini-Bays | B110: =B86 -> 0 | C110: 0.8 | D110: =C110*D111 -> 1280 | E110: =B110*D110*$C$29 -> 0 | F110: =E110/'Financial Summary'!$E$3 -> 0 | G110: =E45 -> 0.41608253 | H110: =E110*G110 -> 0 | I110: =H110/'Financial Summary'!$E$3 -> 0
A111: Standard Bays | B111: =B87 -> 25 | C111: 1 | D111: =B45*C111*B106 -> 1600 | E111: =B111*D111*$C$29 -> 6280000 | F111: =E111/'Financial Summary'!$E$3 -> 1711171.7 | G111: =F45 -> 0.41608253 | H111: =E111*G111 -> 2612998.3 | I111: =H111/'Financial Summary'!$E$3 -> 711988.63
A112: Premium Bays | B112: =B88 -> 0 | C112: 4 | D112: =C112*D111 -> 6400 | E112: =B112*D112*$C$29 -> 0 | F112: =E112/'Financial Summary'!$E$3 -> 0 | G112: =G45 -> 0.27738835 | H112: =E112*G112 -> 0 | I112: =H112/'Financial Summary'!$E$3 -> 0
A113: Hospitality Bays | B113: =B89 -> 0 | C113: 12 | D113: =D111*C113 -> 19200 | E113: =B113*D113*$C$29 -> 0 | F113: =E113/'Financial Summary'!$E$3 -> 0 | G113: =H45 -> 0.20804126 | H113: =E113*G113 -> 0 | I113: =H113/'Financial Summary'!$E$3 -> 0
A114: TOTAL | B114: =SUM(B110:B113) -> 25 | D114: =E114/B114/$C$29 -> 1600 | E114: =SUM(E110:E113) -> 6280000 | F114: =SUM(F110:F113) -> 1711171.7 | G114: =H114/E114 -> 0.41608253 | H114: =SUM(H110:H113) -> 2612998.3 | I114: =SUM(I110:I113) -> 711988.63
A115: Unescalated
A117: DISTINCT USERS | B117: # BAYS | C117: HOURS USED PER BAY | F117: NUMBER OF XRANGERS
C118: Daily | D118: Per Annum | E118: All Bays | F118: Users Per Bay | G118: Avg Time (Hrs) | H118: Xrangers | I118: Per Bay
A119: Mini-Bays | B119: =B110 -> 0 | C119: =G110*$B$106 -> 3.3286602 | D119: =C119*$C$29 -> 522.59965 | E119: =D119*B119 -> 0 | F119: 4 | G119: 2 | H119: =E119/G119*F119 -> 0 | I119: =H119/B119 -> #DIV/0!
...

Sheet Hard + Soft Costs
A1: HARD COST SUMMARY | E1: ='Financial Summary'!M1 -> 45135
A3: Facility Size | B3: ='Area Schedule'!B32 -> 8652 | C3: =B3*'Area Schedule'!B3 -> 93130.128
A5: FACILITY HARD COST SUMMARY
A6: Main Facility | D6: AED psf GFA | E6: AED | F6: USD
A7: Substructure | D7: =E7/$C$3 -> 41.748037 | E7: =SUM(E45:E46) -> 3888000 | F7: =E7/'Financial Summary'!$E$3 -> 1059400.5
A8: Superstructure | D8: =E8/$C$3 -> 204.36485 | E8: =SUM(E9:E13) -> 19032525 | F8: =SUM(F9:F13) -> 5185974.1
A9: Structure | D9: =E9/$C$3 -> 54.413111 | E9: =SUM(E49:E57) -> 5067500 | F9: =E9/'Financial Summary'!$E$3 -> 1380790.2
A10: Roof | D10: =E10/$C$3 -> 45.168788 | E10: =SUM(E59:E64) -> 4206575 | F10: =E10/'Financial Summary'!$E$3 -> 1146205.7
A11: Stairs & Ramps | D11: =E11/$C$3 -> 2.6844159 | E11: =SUM(E66) -> 250000 | F11: =E11/'Financial Summary'!$E$3 -> 68119.891
A12: Façade | D12: =E12/$C$3 -> 79.422741 | E12: =SUM(E68:E79) -> 7396650 | F12: =E12/'Financial Summary'!$E$3 -> 2015436
A13: Internal Walls & Doors | D13: =E13/$C$3 -> 22.675798 | E13: =SUM(E80:E83) -> 2111800 | F13: =E13/'Financial Summary'!$E$3 -> 575422.34
A14: Finishes | D14: =E14/$C$3 -> 125.14962 | E14: =SUM(E87:E121) -> 11655200 | F14: =E14/'Financial Summary'!$E$3 -> 3175803.8
A15: MEP Installations | D15: =E15/$C$3 -> 206.55507 | E15: =SUM(E123:E125) -> 19236500 | F15: =E15/'Financial Summary'!$E$3 -> 5241553.1
A16: Total - Base Facility Cost | D16: =E16/$C$3 -> 577.81758 | E16: =E7+E8+E14+E15 -> 53812225 | F16: =F7+F8+F14+F15 -> 14662732
A17: Outfield | D17: =E17/$C$3 -> 107.37664 | E17: =E129 -> 10000000 | F17: =E17/'Financial Summary'!$E$3 -> 2724795.6
A18: Exterior Works | D18: =E18/$C$3 -> 82.680011 | E18: =E130 -> 7700000 | F18: =E18/'Financial Summary'!$E$3 -> 2098092.6
A19: Total - Base Facility Cost with Outfield & External Works | D19: =E19/$C$3 -> 767.87423 | E19: =SUM(E16:E18) -> 71512225 | F19: =SUM(F16:F18) -> 19485620
A20: Preliminaries | D20: =E20/$C$3 -> 65.269309 | E20: =E134 -> 6078539.1 | F20: =E20/'Financial Summary'!$E$3 -> 1656277.7
A21: Total Facility Cost w/ XRange Technology | D21: =E21/$C$3 -> 833.14354 | E21: =SUM(E19:E20) -> 77590764 | F21: =SUM(F19:F20) -> 21141898
A22: Contingency | D22: =E22/$C$3 -> 124.97153 | E22: =E138 -> 11638615 | F22: =E22/'Financial Summary'!$E$3 -> 3171284.6
A23: =A140 -> Regional Design Discount | D23: =E23/$C$3 -> -874.80071 | E23: =E140 -> -81470302
A24: TOTAL HARD COSTS | D24: =E24/$C$3 -> 83.314354 | E24: =SUM(E21:E23) -> 7759076.4 | F24: =SUM(F21:F22) -> 24313182
A26: XRANGE TECHNOLOGY COST SUMMARY
D27: AED psf GFA | E27: AED | F27: =F6 -> USD
A28: XRange Tech | D28: =E28/$C$3 -> 139.58963 | E28: =E150 -> 13000000 | F28: =E28/'Financial Summary'!$E$3 -> 3542234.3
A30: TOTAL XRANGE TECHNOLOGY COSTS | D30: =E30/$C$3 -> 139.58963 | E30: =SUM(E28:E29) -> 13000000 | F30: =SUM(F28:F29) -> 3542234.3
D31: AED psf GFA | E31: AED | F31: =F27 -> USD
A32: Design Costs - Facility, Outfield & Grounds (incl. contingency) | B32: on Facility Costs | C32: 0.12 | D32: =E32/$C$3 -> 9.9977224 | E32: =E24*C32 -> 931089.17 | F32: =E32/'Financial Summary'!$E$3 -> 253702.77
A33: Project Management Costs | B33: on Facility Costs | C33: 0.02 | D33: =E33/$C$3 -> 1.6662871 | E33: =E24*C33 -> 155181.53 | F33: =E33/'Financial Summary'!$E$3 -> 42283.795
A34: XRange Integration Fees (incl. in XRange Tech) | B34: on XRange Costs | C34: 0 | D34: =E34/$C$3 -> 0 | E34: =C34*E30 -> 0 | F34: =E34/'Financial Summary'!$E$3 -> 0
A36: TOTAL SOFT COSTS | D36: =E36/$C$3 -> 11.66401 | E36: =SUM(E32:E35) -> 1086270.7 | F36: =SUM(F32:F35) -> 295986.57
A41: ASSUMPTIONS
A43: Main Facility | B43: Quantity | C43: Unit | D43: Rate | E43: Total | F43: Total
A44: Substructure | E44: AED | F44: =F31 -> USD
A45: Raft slab to Ground Floor | B45: =SUM('Area Schedule'!B6:B11) -> 2598 | C45: m2 | D45: 1250 | E45: =D45*B45 -> 3247500 | F45: =E45/'Financial Summary'!$E$3 -> 884877.38
A46: Raft slab to Hitting Bays | B46: =SUM('Area Schedule'!B12:B13) -> 854 | C46: m2 | D46: 750 | E46: =D46*B46 -> 640500 | F46: =E46/'Financial Summary'!$E$3 -> 174523.16
A47: Superstructure
A48: Frame
A49: Columns to Ground Floor | B49: =SUM('Area Schedule'!B16:B20) -> 2600 | C49: m2 | D49: 300 | E49: =D49*B49 -> 780000 | F49: =E49/'Financial Summary'!$E$3 -> 212534.06
A50: Columns to Level 1 | B50: =SUM('Area Schedule'!B23:B29) -> 2600 | C50: m2 | D50: 300 | E50: =D50*B50 -> 780000 | F50: =E50/'Financial Summary'!$E$3 -> 212534.06
A51: Columns to Level 2 | B51: =SUM('Area Schedule'!B23:B25)+'Area Schedule'!B29 -> 825 | C51: m2 | D51: 300 | E51: =D51*B51 -> 247500 | F51: =E51/'Financial Summary'!$E$3 -> 67438.692
A52: Staircores | B52: 2 | C52: No | D52: 200000 | E52: =D52*B52 -> 400000 | F52: =E52/'Financial Summary'!$E$3 -> 108991.83
A53: Upper Floors
A54: Suspended slab to Level 1 | B54: =B50-B55 -> 825 | C54: m2 | D54: 550 | E54: =D54*B54 -> 453750 | F54: =E54/'Financial Summary'!$E$3 -> 123637.6
A55: Suspended slab to Level 1 Hitting Bays | B55: ='Area Schedule'!B19 -> 1775 | C55: m2 | D55: 550 | E55: =D55*B55 -> 976250 | F55: =E55/'Financial Summary'!$E$3 -> 266008.17
A56: Suspended slab to Level 2 | B56: ='Area Schedule'!B30-B57 -> 1319 | C56: m2 | D56: 550 | E56: =D56*B56 -> 725450 | F56: =E56/'Financial Summary'!$E$3 -> 197670.3
A57: Suspended slab to Level 2 Hitting Bays | B57: ='Area Schedule'!B26+'Area Schedule'!B27 -> 1281 | C57: m2 | D57: 550 | E57: =D57*B57 -> 704550 | F57: =E57/'Financial Summary'!$E$3 -> 191975.48
A58: Roof
A59: Suspended roof slab to Level 2 | B59: =B51 -> 825 | C59: m2 | D59: 450 | E59: =D59*B59 -> 371250 | F59: =E59/'Financial Summary'!$E$3 -> 101158.04
A60: Metal roofing system incl. secondary support | B60: =B59 -> 825 | C60: m2 | D60: 475 | E60: =D60*B60 -> 391875 | F60: =E60/'Financial Summary'!$E$3 -> 106777.93
A61: Waterproofing to Level 1 Hitting Bays | B61: =B55 -> 1775 | C61: m2 | D61: 275 | E61: =D61*B61 -> 488125 | F61: =E61/'Financial Summary'!$E$3 -> 133004.09
A62: Waterproofing to Level 2 Hitting Bays | B62: =B57 -> 1281 | C62: m2 | D62: 275 | E62: =D62*B62 -> 352275 | F62: =E62/'Financial Summary'!$E$3 -> 95987.738
A63: Canopy roof to Level 2 Hitting Bays | B63: 1775 | C63: m2 | D63: 1250 | E63: =D63*B63 -> 2218750 | F63: =E63/'Financial Summary'!$E$3 -> 604564.03
A64: Soffit treatment | B64: =B46 -> 854 | C64: m2 | D64: 450 | E64: =D64*B64 -> 384300 | F64: =E64/'Financial Summary'!$E$3 -> 104713.9
A65: Stairs & Ramps
A66: Feature Stair G - L2 Terrace | B66: 1 | C66: Item | D66: 250000 | E66: =D66*B66 -> 250000 | F66: =E66/'Financial Summary'!$E$3 -> 68119.891
A67: Façade
A68: Blockwork with rendered finish | B68: =144*14 -> 2016 | C68: m2 | D68: 650 | E68: =D68*B68 -> 1310400 | F68: =E68/'Financial Summary'!$E$3 -> 357057.22
A69: Masonry wall with cladding | B69: =4*16*5+2*16*5+4*16*5 -> 800 | C69: m2 | D69: 950 | E69: =D69*B69 -> 760000 | F69: =E69/'Financial Summary'!$E$3 -> 207084.47
A70: Screens to Hitting Bays | B70: =41+9+9+6+6 -> 71 | C70: Nr | D70: 5000 | E70: =D70*B70 -> 355000 | F70: =E70/'Financial Summary'!$E$3 -> 96730.245
A71: Curtain Wall To GF F+B | B71: =70*4.5 -> 315 | C71: m2 | D71: 2250 | E71: =D71*B71 -> 708750 | F71: =E71/'Financial Summary'!$E$3 -> 193119.89
A72: Curtain Wall To L1 Circulation | B72: =144*4.5 -> 648 | C72: m2 | D72: 2250 | E72: =D72*B72 -> 1458000 | F72: =E72/'Financial Summary'!$E$3 -> 397275.2
A73: Curtain Wall To L2 VVIP / VIP | B73: =100*4.5 -> 450 | C73: m2 | D73: 2250 | E73: =D73*B73 -> 1012500 | F73: =E73/'Financial Summary'!$E$3 -> 275885.56
A74: Main Entrance Doors | B74: 1 | C74: Item | D74: 250000 | E74: =D74*B74 -> 250000 | F74: =E74/'Financial Summary'!$E$3 -> 68119.891
A75: Doors to Terraces / Hitting Bays | B75: 16 | C75: Nr | D75: 20000 | E75: =D75*B75 -> 320000 | F75: =E75/'Financial Summary'!$E$3 -> 87193.46
A76: Glazed balustrades to L2 Terrace | B76: 20 | C76: m2 | D76: 2000 | E76: =D76*B76 -> 40000 | F76: =E76/'Financial Summary'!$E$3 -> 10899.183
A77: Fall prevention to L1 & L2 | B77: =2*144 -> 288 | C77: m | D77: 1500 | E77: =D77*B77 -> 432000 | F77: =E77/'Financial Summary'!$E$3 -> 117711.17
A78: Branded signage | B78: 1 | C78: Item | D78: 750000 | E78: =D78*B78 -> 750000 | F78: =E78/'Financial Summary'!$E$3 -> 204359.67
A79: Internal Walls & Doors
A80: Ground Floor | B80: =B45 -> 2598 | C80: m2 | D80: 350 | E80: =D80*B80 -> 909300 | F80: =E80/'Financial Summary'!$E$3 -> 247765.67
A81: Level 1 | B81: =B54 -> 825 | C81: m2 | D81: 350 | E81: =D81*B81 -> 288750 | F81: =E81/'Financial Summary'!$E$3 -> 78678.474
A82: Level 2 | B82: =B51 -> 825 | C82: m2 | D82: 350 | E82: =D82*B82 -> 288750 | F82: =E82/'Financial Summary'!$E$3 -> 78678.474
A83: Allow for operable walls to VIP / VVIP | B83: 5 | C83: Nr | D83: 125000 | E83: =D83*B83 -> 625000 | F83: =E83/'Financial Summary'!$E$3 -> 170299.73
A84: Finishes
A85: Note: Wall / Floor / Ceiling
A86: Ground Floor
A87: Lobby / Circulation | B87: ='Area Schedule'!B6 -> 647 | C87: m2 | D87: 1150 | E87: =D87*B87 -> 744050 | F87: =E87/'Financial Summary'!$E$3 -> 202738.42
A88: Restaurant | B88: ='Area Schedule'!B7 -> 997 | C88: m2 | D88: 850 | E88: =D88*B88 -> 847450 | F88: =E88/'Financial Summary'!$E$3 -> 230912.81
A89: Amenities | B89: ='Area Schedule'!B8 -> 144 | C89: m2 | D89: 1450 | E89: =D89*B89 -> 208800 | F89: =E89/'Financial Summary'!$E$3 -> 56893.733
A90: Administration | B90: ='Area Schedule'!B9 -> 170 | C90: m2 | D90: 350 | E90: =D90*B90 -> 59500 | F90: =E90/'Financial Summary'!$E$3 -> 16212.534
A91: BOH / MEP / Kitchen | B91: ='Area Schedule'!B10 -> 578 | C91: m2 | D91: 350 | E91: =D91*B91 -> 202300 | F91: =E91/'Financial Summary'!$E$3 -> 55122.616
A92: Lift Core | B92: ='Area Schedule'!B11 -> 62 | C92: m2 | E92: Not Applicable | F92: Not Applicable
A93: Mini-Bays | B93: ='Area Schedule'!B12 -> 427 | C93: m2 | D93: 250 | E93: =D93*B93 -> 106750 | F93: =E93/'Financial Summary'!$E$3 -> 29087.193
A94: Academy Bays | B94: ='Area Schedule'!B13 -> 427 | C94: m2 | D94: 250 | E94: =D94*B94 -> 106750 | F94: =E94/'Financial Summary'!$E$3 -> 29087.193
A95: Level 1
A96: Circulation | B96: ='Area Schedule'!B16 -> 460 | C96: m2 | D96: =D87 -> 1150 | E96: =D96*B96 -> 529000 | F96: =E96/'Financial Summary'!$E$3 -> 144141.69
A97: Amenities | B97: ='Area Schedule'!B17 -> 144 | C97: m2 | D97: =D89 -> 1450 | E97: =D97*B97 -> 208800 | F97: =E97/'Financial Summary'!$E$3 -> 56893.733
A98: BOH / MEP / Kitchen | B98: ='Area Schedule'!B18 -> 159 | C98: m2 | D98: =D91 -> 350 | E98: =D98*B98 -> 55650 | F98: =E98/'Financial Summary'!$E$3 -> 15163.488
A99: Lift Core | B99: ='Area Schedule'!B20 -> 62 | C99: m2 | E99: Not Applicable | F99: Not Applicable
A100: Standard Bay | B100: ='Area Schedule'!B19 -> 1775 | C100: m2 | D100: =D94 -> 250 | E100: =D100*B100 -> 443750 | F100: =E100/'Financial Summary'!$E$3 -> 120912.81
A101: Level 2
A102: Circulation | B102: ='Area Schedule'!B23 -> 460 | C102: m2 | D102: =D96 -> 1150 | E102: =D102*B102 -> 529000 | F102: =E102/'Financial Summary'!$E$3 -> 144141.69 | G102: 446480
A103: Amenities | B103: ='Area Schedule'!B24 -> 144 | C103: m2 | D103: =D97 -> 1450 | E103: =D103*B103 -> 208800 | F103: =E103/'Financial Summary'!$E$3 -> 56893.733 | G103: 390670
A104: BOH / MEP / Kitchen | B104: ='Area Schedule'!B25 -> 159 | C104: m2 | D104: =D98 -> 350 | E104: =D104*B104 -> 55650 | F104: =E104/'Financial Summary'!$E$3 -> 15163.488 | G104: 446480
A105: Lift Core | B105: ='Area Schedule'!B29 -> 62 | C105: m2 | E105: Not Applicable | F105: Not Applicable | G105: 1004000
A106: Standard Bay | B106: ='Area Schedule'!B26 -> 607 | C106: m2 | D106: =D100 -> 250 | E106: =D106*B106 -> 151750 | F106: =E106/'Financial Summary'!$E$3 -> 41348.774 | G106: 4464800
A107: VIP | B107: ='Area Schedule'!B27 -> 674 | C107: m2 | D107: 1350 | E107: =D107*B107 -> 909900 | F107: =E107/'Financial Summary'!$E$3 -> 247929.16 | G107: 641815
A108: VVIP | B108: ='Area Schedule'!B28 -> 494 | C108: m2 | D108: =1650 -> 1650 | E108: =D108*B108 -> 815100 | F108: =E108/'Financial Summary'!$E$3 -> 222098.09 | G108: 4883375
A109: FFE | G109: 111620
A110: Note: Wall / Floor / Ceiling | G110: 1953350
...

Sheet XRange Tech & Equipment
A1: XRANGE - SPECIALIST EQUIPMENT & TECH | E1: ='Financial Summary'!M1 -> 45135
A3: SUMMARY
A5: SPECIALIST EQUIPMENT | B5: QTY | C5: DESCRIPTION OF ITEM | D5: COST PER ITEM | E5: TOTAL COST | F5: COMMENTS
B6: # | D6: AED | E6: AED
A7: Right Hand Club Set | B7: 85 | C7: 12 Club Set - Branded | D7: 1400 | E7: =SUM(B7*D7) -> 119000
A8: Left Hand Club Set | B8: 25 | C8: 12 Club Branded Set - Branded | D8: 1500 | E8: =SUM(B8*D8) -> 37500
A9: Kids Right Hand Club Set | B9: 20 | C9: 12 Club Branded Set - Branded
A10: Kids Left Hand Club Set | B10: 10 | C10: 12 Club Branded Set - Branded
A11: Golf Balls | B11: 130 000 | C11: Branded Golf Balls
A12: Hopper H50, 50,000 ball cap. | B12: 85 | E12: =SUM(B12*D12) -> 0
A13: Elevator 2.3m hopper | B13: 85 | E13: =SUM(B13*D13) -> 0
A14: Automatic outfeed, Hopper-Blow | B14: 85 | E14: =SUM(B14*D14) -> 0
A15: Hopper H22 extended legs | B15: 85 | E15: =SUM(B15*D15) -> 0
A16: Blower Module 3.0 kW | B16: 85 | E16: =SUM(B16*D16) -> 0
A17: Blowfill manifold | B17: 85 | E17: =SUM(B17*D17) -> 0
A18: Ball stop, complete | B18: 85 | E18: =SUM(B18*D18) -> 0
A19: 6Photocell PNP V H&L level 1 | B19: 85 | E19: =SUM(B19*D19) -> 0
A20: Holder for photocell H/L ex. | B20: 85 | E20: =SUM(B20*D20) -> 0
A21: photocell | B21: 85 | E21: =SUM(B21*D21) -> 0
A22: Kabel Ölflex | B22: 85 | E22: =SUM(B22*D22) -> 0
A23: System Control Filling max | B23: 85 | E23: =SUM(B23*D23) -> 0
... A31: Tee Box Gen 4 | B31: 85 | E31: =SUM(B31*D31) -> 0
A39: TOTAL | B39: =SUM(B7:B31) -> 1840 | D39: =E39/B39/$C59 -> #DIV/0! | E39: =SUM(E7:E31) -> 156500
D45: XRange
E46: USD | F46: AED
B47: Tracking System | C47: Radar | E47: 300000 | F47: =SUM(#REF!*'Financial Summary'!E3) -> #REF!
B48: IT Infrustructure | C48: Server
B49: User Interface | C49: Control Panels
B50: Mega Media | C50: 3D Projection Mapping | D50: 4lg + 4sml Targets | E50: 2800000 | F50: =SUM(#REF!*'Financial Summary'!E3) -> #REF!
C52: Total
E54: 650000
E56: =SUM(E50+E54) -> 3450000

Sheet Area Schedule
A1: AREA SCHEDULE | B1: ='Financial Summary'!M1 -> 45135
A3: sm/sf | B3: 10.764
A5: GROUND FLOOR | B5: sm | C5: sf
A6: LOBBY AND PUBLIC CIRCULATION | B6: 647 | C6: =B6*$B$3 -> 6964.308
A7: MAIN RESTAURANT | B7: 997 | C7: =B7*$B$3 -> 10731.708
A8: TOILETS | B8: 144 | C8: =B8*$B$3 -> 1550.016
A9: ADMIN | B9: 170 | C9: =B9*$B$3 -> 1829.88
A10: BOH/MEP/KITCHEN | B10: 578 | C10: =B10*$B$3 -> 6221.592
A11: VT | B11: 62 | C11: =B11*$B$3 -> 667.368
A12: MINI BAYS - 10 BAYS | B12: 427 | C12: =B12*$B$3 -> 4596.228
A13: ACADEMY - 10 BAYS | B13: 427 | C13: =B13*$B$3 -> 4596.228
B14: =SUM(B6:B13) -> 3452 | C14: =SUM(C6:C13) -> 37157.328
A15: FIRST FLOOR
A16: PUBLIC CIRCULATION | B16: 460 | C16: =B16*$B$3 -> 4951.44
A17: TOILETS | B17: 144 | C17: =B17*$B$3 -> 1550.016
A18: BOH/MEP/KITCHEN | B18: 159 | C18: =B18*$B$3 -> 1711.476
A19: STANDARD BAYS - 42 BAYS | B19: 1775 | C19: =B19*$B$3 -> 19106.1
A20: VT | B20: 62 | C20: =B20*$B$3 -> 667.368
B21: =SUM(B16:B20) -> 2600 | C21: =SUM(C16:C20) -> 27986.4
A22: SECOND FLOOR
A23: PUBLIC CIRCULATION | B23: 460 | C23: =B23*$B$3 -> 4951.44
A24: TOILETS | B24: 144 | C24: =B24*$B$3 -> 1550.016
A25: BOH/MEP/KITCHEN | B25: 159 | C25: =B25*$B$3 -> 1711.476
A26: STANDARD BAYS - 14 BAYS | B26: 607 | C26: =B26*$B$3 -> 6533.748
A27: VIP - 4 BAYS | B27: 674 | C27: =B27*$B$3 -> 7254.936
A28: VVIP - 2 BAYS | B28: 494 | C28: =B28*$B$3 -> 5317.416
A29: VT | B29: 62 | C29: =B29*$B$3 -> 667.368
B30: =SUM(B23:B29) -> 2600 | C30: =SUM(C23:C29) -> 27986.4
A32: TOTAL | B32: =+B30+B21+B14 -> 8652 | C32: =+C30+C21+C14 -> 93130.128
A34: EXTERNAL WORKS
A35: PARKING / DROP OFF / LOADING AREA | B35: 14000 | C35: =B35*$B$3 -> 150696
A36: THE FIELD | B36: 20000 | C36: =B36*$B$3 -> 215280
A37: TOTAL | B37: =SUM(B35:B36) -> 34000 | C37: =SUM(C35:C36) -> 365976
A39: PROPERTY OF XRANGE
A40: Not For Distribution without the express agreement of XRange Management

Sheet Sheet1
